main.py
omron/__init__.py
omron/f4_tcp_serial.py
omron-0.1.6.dist-info/LICENSE.txt
omron-0.1.6.dist-info/METADATA
omron-0.1.6.dist-info/WHEEL
omron-0.1.6.dist-info/top_level.txt
omron-0.1.6.dist-info/RECORD
